ineff/VERSION
ineff/__init__.py
ineff/config.py
ineff/utils.py
inefficient_networks-0.2.1.dist-info/METADATA
inefficient_networks-0.2.1.dist-info/WHEEL
inefficient_networks-0.2.1.dist-info/top_level.txt
inefficient_networks-0.2.1.dist-info/RECORD
