Metadata-Version: 2.1
Name: inefficient-networks
Version: 0.2.1
Summary: Helper functions for Inefficient Networks collection.
Home-page: https://github.com/particle1331/inefficient-networks/
Author: Ron Medina
Author-email: particle1331@gmail.com
License: BSD-3
Classifier: License :: OSI Approved :: MIT License
Classifier: Programming Language :: Python :: 3.9
Requires-Python: >=3.6.0
Requires-Dist: jupyter-book (<0.14.0,>=0.13.0)
Requires-Dist: matplotlib (<3.6.0,>=3.5.1)
Requires-Dist: pydantic (<1.9.0,>=1.8.1)
Requires-Dist: pandas (<1.5.0,>=1.4.0)
Requires-Dist: numpy (<1.23.0,>=1.22.0)
